wandler/__init__.py
wandler/__main__.py
wandler/cli.py
wandler/config.py
wandler-0.0.2.dist-info/licenses/LICENSE
wandler-0.0.2.dist-info/METADATA
wandler-0.0.2.dist-info/WHEEL
wandler-0.0.2.dist-info/entry_points.txt
wandler-0.0.2.dist-info/top_level.txt
wandler-0.0.2.dist-info/RECORD
