Metadata-Version: 2.4
Name: wandler
Version: 0.0.2
Summary: A simple, fast, Python-native task runner
Author-email: Rosshhun Gadde <me@rosshhun.com>
License: MIT License
Project-URL: Homepage, https://github.com/rosshhun/wandler
Classifier: Programming Language :: Python :: 3
Classifier: License :: OSI Approved :: MIT License
Classifier: Operating System :: OS Independent
Requires-Python: >=3.8
License-File: LICENSE
Requires-Dist: PyYAML>=6.0
Requires-Dist: pydantic<3.0,>=2.0
Requires-Dist: typer<1.0,>=0.9
Dynamic: license-file
